dependapy/__init__.py
dependapy/analyzer.py
dependapy/github_api.py
dependapy/main.py
dependapy/py.typed
dependapy/updater.py
dependapy-0.1.1.dist-info/METADATA
dependapy-0.1.1.dist-info/WHEEL
dependapy-0.1.1.dist-info/entry_points.txt
dependapy-0.1.1.dist-info/licenses/LICENSE
dependapy-0.1.1.dist-info/RECORD
