Metadata-Version: 2.4
Name: dependapy
Version: 0.1.1
Summary: A custom dependabot alternative for Python projects
Author-email: stefanposs <hello@stefanposs.com>
License: MIT License
License-File: LICENSE
Keywords: dependabot,dependencies,update
Classifier: Development Status :: 3 - Alpha
Classifier: Environment :: Console
Classifier: Intended Audience :: Developers
Classifier: License :: OSI Approved :: MIT License
Classifier: Programming Language :: Python :: 3.11
Classifier: Programming Language :: Python :: 3.12
Classifier: Programming Language :: Python :: 3.13
Classifier: Topic :: Software Development :: Libraries :: Python Modules
Classifier: Topic :: Software Development :: Version Control
Requires-Python: >=3.11
Requires-Dist: bandit>=1.7.5
Requires-Dist: packaging==23.2
Requires-Dist: pygithub==2.6.1
Requires-Dist: pyright>=1.1.401
Requires-Dist: pytest-asyncio>=0.23.8
Requires-Dist: pytest-cov>=4.1.0
Requires-Dist: pytest-timeout>=2.4.0
Requires-Dist: requests==2.32.4
Requires-Dist: ruff>=0.3.2
Requires-Dist: tomli==2.0.1
Requires-Dist: twine>=6.0.1
